setup.py
AIDE/__init__.py
AIDE/cdc_functions.py
AIDE/expert_inputs.py
AIDE/floc_model.py
AIDE/init.py
AIDE/materials_database.py
AIDE/physchem.py
AIDE/pipedatabase.py
AIDE/units.py
AIDE/utility.py
AIDE.egg-info/PKG-INFO
AIDE.egg-info/SOURCES.txt
AIDE.egg-info/dependency_links.txt
AIDE.egg-info/not-zip-safe
AIDE.egg-info/requires.txt
AIDE.egg-info/top_level.txt